chinillapos.cpython-310-x86_64-linux-gnu.so
chinillapos-1.0.12.dist-info/METADATA
chinillapos-1.0.12.dist-info/top_level.txt
chinillapos-1.0.12.dist-info/RECORD
chinillapos-1.0.12.dist-info/WHEEL
chinillapos-1.0.12.dist-info/LICENSE
