Metadata-Version: 2.1
Name: chinillapos
Version: 1.0.12
Summary: Chinilla proof of space plotting, proving, and verifying (wraps C++)
Home-page: https://github.com/Chinilla/chinillapos
Author: Mariano Sorgente
Author-email: mariano@chinilla.net
License: Apache License
Requires-Python: >=3.7
License-File: LICENSE
